Metadata-Version: 2.1
Name: physicsfront-mqca
Version: 0.1.0
Summary: Utility package for qiskit and physicsfront-qiskit
Home-page: https://github.com/sam-pf/pf-mqca
Author: Physics Front LLC
Author-email: info@physicsfront.com
License: Apache 2.0
Project-URL: GitHub, https://github.com/sam-pf/pf-mqca
Platform: Posix; MacOS X; Windows
Classifier: Development Status :: 3 - Alpha
Classifier: Intended Audience :: Developers
Classifier: Intended Audience :: Education
Classifier: License :: OSI Approved :: Apache Software License
Classifier: Programming Language :: Python
Classifier: Programming Language :: Python :: 3
Classifier: Programming Language :: Python :: 3.8
Classifier: Programming Language :: Python :: 3.9
Classifier: Programming Language :: Python :: 3.10
Classifier: Programming Language :: Python :: 3.11
Classifier: Operating System :: OS Independent
Classifier: Topic :: Internet
Classifier: Topic :: Scientific/Engineering :: Physics
Classifier: Topic :: Security :: Cryptography
Requires-Python: >=3.8
Provides-Extra: mpl
License-File: LICENSE
